immunity_utils/__init__.py
immunity_utils/admin.py
immunity_utils/base.py
immunity_utils/fields.py
immunity_utils/loaders.py
immunity_utils/qa.py
immunity_utils/settings.py
immunity_utils/staticfiles.py
immunity_utils/storage.py
immunity_utils/tasks.py
immunity_utils/test_selenium_mixins.py
immunity_utils/tests.py
immunity_utils/utils.py
immunity_utils/validators.py
immunity_utils/admin_theme/__init__.py
immunity_utils/admin_theme/admin.py
immunity_utils/admin_theme/apps.py
immunity_utils/admin_theme/checks.py
immunity_utils/admin_theme/context_processor.py
immunity_utils/admin_theme/dashboard.py
immunity_utils/admin_theme/email.py
immunity_utils/admin_theme/filters.py
immunity_utils/admin_theme/menu.py
immunity_utils/admin_theme/settings.py
immunity_utils/admin_theme/system_info.py
immunity_utils/admin_theme/theme.py
immunity_utils/admin_theme/views.py
immunity_utils/admin_theme/static/admin/css/help-text-stacked.css
immunity_utils/admin_theme/static/admin/css/openwisp-info.css
immunity_utils/admin_theme/static/admin/css/openwisp.css
immunity_utils/admin_theme/static/admin/css/ow-auto-filter.css
immunity_utils/admin_theme/static/admin/css/ow-dashboard.css
immunity_utils/admin_theme/static/admin/css/ow-filters.css
immunity_utils/admin_theme/static/admin/fonts/LICENSE.txt
immunity_utils/admin_theme/static/admin/fonts/README.txt
immunity_utils/admin_theme/static/admin/fonts/Roboto-Bold-webfont.woff
immunity_utils/admin_theme/static/admin/fonts/Roboto-Light-webfont.woff
immunity_utils/admin_theme/static/admin/fonts/Roboto-Regular-webfont.woff
immunity_utils/admin_theme/static/admin/js/menu.js
immunity_utils/admin_theme/static/admin/js/ow-auto-filter.js
immunity_utils/admin_theme/static/admin/js/ow-dashboard.js
immunity_utils/admin_theme/static/admin/js/ow-filter.js
immunity_utils/admin_theme/static/admin/vendor/js/plotly-cartesian.min.js
immunity_utils/admin_theme/static/drf-yasg/ow-drf-yasg.css
immunity_utils/admin_theme/static/rest_framework/css/browsable-api.css
immunity_utils-1.1a0.dist-info/LICENSE
immunity_utils-1.1a0.dist-info/METADATA
immunity_utils-1.1a0.dist-info/WHEEL
immunity_utils-1.1a0.dist-info/entry_points.txt
immunity_utils-1.1a0.dist-info/top_level.txt
immunity_utils-1.1a0.dist-info/RECORD
