Metadata-Version: 2.1
Name: immunity-utils
Version: 1.1a0
Summary: Immunity 2 Utilities
Home-page: http://immunity.org
Download-URL: https://github.com/edge-servers/immunity-utils/releases
Author: Rohith Asrk
Author-email: rohith.asrk@gmail.com
License: BSD-3-Clause
Keywords: django,netjson,openwrt,networking,immunity
Platform: Platform Independent
Classifier: Development Status :: 3 - Alpha
Classifier: Environment :: Web Environment
Classifier: Topic :: Internet :: WWW/HTTP
Classifier: Topic :: System :: Networking
Classifier: Intended Audience :: Developers
Classifier: License :: OSI Approved :: BSD License
Classifier: Operating System :: OS Independent
Classifier: Framework :: Django
Classifier: Programming Language :: Python :: 3
License-File: LICENSE
Requires-Dist: django-model-utils ~=4.3.1
Requires-Dist: django-compress-staticfiles ~=1.0.1b
Requires-Dist: django-admin-autocomplete-filter ~=0.7.1
Requires-Dist: swapper ~=1.3.0
Requires-Dist: urllib3 <3.0.0,>=2.0.0
Provides-Extra: celery
Requires-Dist: celery ~=5.3.0 ; extra == 'celery'
Provides-Extra: qa
Requires-Dist: black ~=22.3.0 ; extra == 'qa'
Requires-Dist: flake8 <=3.9 ; extra == 'qa'
Requires-Dist: isort ~=5.0 ; extra == 'qa'
Requires-Dist: readme-renderer ~=28.0 ; extra == 'qa'
Requires-Dist: coveralls ~=3.0.0 ; extra == 'qa'
Requires-Dist: tblib ~=3.0.0 ; extra == 'qa'
Provides-Extra: rest
Requires-Dist: djangorestframework ~=3.14.0 ; extra == 'rest'
Requires-Dist: django-filter ~=23.2 ; extra == 'rest'
Requires-Dist: drf-yasg ~=1.21.7 ; extra == 'rest'
Provides-Extra: selenium
Requires-Dist: selenium ~=4.10.0 ; extra == 'selenium'
